aiodgram/__init__.py
aiodgram/beautiful.py
aiodgram/buttons.py
aiodgram/darktube.py
aiodgram/database.py
aiodgram/exceptions.py
aiodgram/infos.py
aiodgram/library.py
aiodgram/loading.py
aiodgram/logged.py
aiodgram/meta_data.py
aiodgram/password_maker.py
aiodgram/addition/__init__.py
aiodgram/addition/beautiful.py
aiodgram/addition/loading.py
aiodgram/addition/password_maker.py
aiodgram/main/__init__.py
aiodgram/main/library.py
aiodgram/meta/__init__.py
aiodgram/meta/meta_data.py
aiodgram-2.6.3.dist-info/METADATA
aiodgram-2.6.3.dist-info/WHEEL
aiodgram-2.6.3.dist-info/top_level.txt
aiodgram-2.6.3.dist-info/RECORD
