Metadata-Version: 2.1
Name: aiodgram
Version: 2.6.3
Summary: This library from easy work with aiogram
Author: Darkangel, Arkeep
Author-email: fvovva@gmail.com
Keywords: telegram aiogram aiodgram
Classifier: Programming Language :: Python :: 3
Classifier: License :: OSI Approved :: MIT License
Classifier: Operating System :: OS Independent
Requires-Python: >=3.9
Requires-Dist: aiogram <=2.25.2
Requires-Dist: colorama
Requires-Dist: pytube
